{
    "Raw_Data_Info.": {
        "Raw_data_ID": "H-220805_A26_N-03_001",
        "Location_ID": 26,
        "type_ID": "A",
        "Type_Description": "추락",
        "process_ID": "b",
        "Copyright": "Hulan Inc.",
        "Resolution": "1920, 1080",
        "Date": "2022-08-05",
        "Main_class_ID": "SO-19",
        "Main_item_ID": "AT",
        "Situation_ID": "N-03",
        "Start_Time": "22:48:11",
        "End_Time": "22:48:54",
        "Length": 43,
        "GPS": "37.016927, 127.270752",
        "Site_Condition": "2",
        "Weather_Information": "1",
        "Wind_Speed": "2",
        "FPS": 30,
        "device": 1,
        "File_Extension": "mp4"
    },
    "Source_Data_Info.": {
        "Source_Data": "H-220805_A26_N-03_001_0001",
        "Extraction_Time": "00:00:01.10",
        "File_extension": "jpg"
    },
    "Learning_Data_Info.": {
        "Path": "./5대사고유형/추락/비정상/N-03/",
        "Json_Data_ID": "H-220805_A26_N-03_001_0001",
        "File_Extension": "JSON",
        "Annotations": [
            {
                "class_ID": "N-03",
                "type": "bbox",
                "value": [
                    465.9,
                    465.31,
                    706.3,
                    343.49
                ]
            },
            {
                "class_ID": "SO-19",
                "type": "polygon",
                "item_ID": "ATO",
                "value": [
                    474.07,
                    612.01,
                    472.56,
                    614.2,
                    474.91,
                    615.55,
                    475.42,
                    618.08,
                    474.91,
                    620.6,
                    638.96,
                    771.52,
                    640.98,
                    772.7,
                    643.51,
                    773.37,
                    646.04,
                    773.2,
                    648.4,
                    772.19,
                    650.59,
                    770.84,
                    652.61,
                    768.99,
                    654.12,
                    766.8,
                    718.6,
                    737.0,
                    755.06,
                    722.75,
                    1161.17,
                    802.8,
                    1166.2,
                    793.99,
                    1167.88,
                    626.77,
                    1000.24,
                    602.46,
                    1024.13,
                    592.82,
                    1057.18,
                    579.17,
                    1059.7,
                    578.33,
                    1061.72,
                    576.64,
                    1062.9,
                    574.12,
                    1063.24,
                    571.59,
                    1062.4,
                    569.07,
                    1034.1,
                    556.94,
                    1032.92,
                    550.03,
                    900.87,
                    473.4,
                    894.64,
                    471.54,
                    890.26,
                    467.0,
                    777.24,
                    505.9,
                    686.18,
                    537.69,
                    678.91,
                    542.35,
                    668.14,
                    539.73,
                    661.44,
                    547.3,
                    637.0,
                    556.61
                ]
            }
        ]
    }
}