{
	"Raw_Data_Info.": {
		"Raw_data_ID": "H-221020_D11_Y-36_002",
		"Location_ID": 11,
		"type_ID": "D",
		"Type_Description": "화재",
		"process_ID": "o",
		"Copyright": "Hulan Inc.",
		"Resolution": "1920, 1080",
		"Date": "2022-10-20",
		"Main_class_ID": "SO-40",
		"Main_item_ID": "TY",
		"Situation_ID": "Y-36",
		"Start_Time": "15:38:58",
		"End_Time": "15:40:14",
		"Length": 76,
		"GPS": "35.128858, 128.561399",
		"Site_Condition": "2",
		"Weather_Information": "1",
		"Wind_Speed": "2",
		"FPS": 30,
		"device": 1,
		"File_Extension": "mp4"
	},
	"Source_Data_Info.": {
		"Source_Data": "H-221020_D11_Y-36_002_0001",
		"Extraction_Time": "00:00:00.57",
		"File_extension": "jpg"
	},
	"Learning_Data_Info.": {
		"Path": "./5대사고유형/화재/정상/Y-36/",
		"Json_Data_ID": "H-221020_D11_Y-36_002_0001",
		"File_Extension": "JSON",
		"Annotations": [
			{
				"class_ID": "SO-40",
				"type": "polygon",
				"item_ID": "TYO",
				"value": [
					1050.11,
					900.84,
					1052.67,
					825.56,
					1056.95,
					802.46,
					1065.93,
					785.78,
					1072.78,
					778.51,
					1079.62,
					774.66,
					1083.47,
					766.96,
					1088.6,
					762.26,
					1094.59,
					760.97,
					1109.99,
					750.71,
					1118.11,
					744.72,
					1125.38,
					745.15,
					1131.37,
					749.85,
					1124.96,
					752.85,
					1114.69,
					758.41,
					1109.13,
					763.54,
					1112.13,
					768.25,
					1119.4,
					769.1,
					1125.38,
					769.1,
					1136.08,
					776.37,
					1132.66,
					778.94,
					1127.52,
					776.37,
					1118.11,
					774.66,
					1113.84,
					775.52,
					1114.69,
					781.08,
					1112.13,
					789.63,
					1122.39,
					796.9,
					1129.66,
					807.6,
					1130.95,
					840.1,
					1130.52,
					915.81,
					1130.09,
					931.63,
					1123.25,
					944.46,
					1121.54,
					953.44,
					1112.55,
					957.72,
					1093.73,
					961.14,
					1068.5,
					955.16,
					1063.37,
					950.02,
					1057.7,
					927.9,
					1059.7,
					908.2
				]
			},
			{
				"class_ID": "Y-36",
				"type": "bbox",
				"value": [
					565.5,
					0.0,
					1343.75,
					964.1
				]
			},
			{
				"class_ID": "SO-23",
				"type": "polygon",
				"item_ID": "TYO",
				"value": [
					622.95,
					921.45,
					626.18,
					674.1,
					598.34,
					653.38,
					579.56,
					624.89,
					574.38,
					578.27,
					578.27,
					554.96,
					587.98,
					539.42,
					577.62,
					439.7,
					596.4,
					411.21,
					632.66,
					384.67,
					621.0,
					369.13,
					628.77,
					353.59,
					646.26,
					347.11,
					664.39,
					347.76,
					673.45,
					345.17,
					666.98,
					328.98,
					683.16,
					321.86,
					705.83,
					326.39,
					709.07,
					336.75,
					711.01,
					357.47,
					731.73,
					366.54,
					781.59,
					380.78,
					832.09,
					380.13,
					838.57,
					393.08,
					830.15,
					410.57,
					815.9,
					459.6,
					771.87,
					506.4,
					747.27,
					533.59,
					745.33,
					602.23,
					743.7,
					772.2,
					764.1,
					611.29,
					770.58,
					595.75,
					793.24,
					582.15,
					800.36,
					518.7,
					822.38,
					516.11,
					843.75,
					516.11,
					876.12,
					521.94,
					894.25,
					528.41,
					886.48,
					587.33,
					902.67,
					598.34,
					912.38,
					619.06,
					894.25,
					879.36,
					885.83,
					902.02,
					890.37,
					923.39,
					878.71,
					933.75,
					827.56,
					946.7,
					791.3,
					944.11,
					743.38,
					925.33,
					728.49,
					937.63,
					694.17,
					946.05,
					664.39,
					945.4,
					635.9,
					938.93
				]
			},
			{
				"class_ID": "SO-32",
				"type": "polygon",
				"item_ID": "TYO",
				"value": [
					1154.8,
					774.8,
					1445.18,
					761.52,
					1654.58,
					747.97,
					1653.97,
					722.72,
					1787.0,
					717.79,
					1920.0,
					713.62,
					1920.0,
					61.14,
					1699.54,
					43.99,
					1592.99,
					83.41,
					1594.22,
					56.31,
					1435.94,
					37.22,
					1357.1,
					69.86,
					1362.62,
					0.0,
					865.0,
					0.0,
					869.31,
					250.32,
					869.24,
					513.1,
					871.05,
					727.91,
					900.83,
					727.0,
					1044.84,
					714.1,
					1083.02,
					738.12,
					1109.1,
					750.4,
					1118.11,
					744.72,
					1125.6,
					745.5,
					1131.1,
					749.2,
					1129.83,
					752.9,
					1119.36,
					757.21,
					1142.6,
					770.3
				]
			}
		]
	}
}